pymoodleclient/__init__.py
pymoodleclient/client.py
pymoodleclient/endpoints/__init__.py
pymoodleclient/endpoints/base/__init__.py
pymoodleclient/endpoints/base/base_endpoint.py
pymoodleclient/endpoints/base/base_response_object.py
pymoodleclient/endpoints/course/__init__.py
pymoodleclient/endpoints/course/course_endpoints.py
pymoodleclient/endpoints/course/course_responses.py
pymoodleclient/request_params.py
pymoodleclient-0.2.0b1.dist-info/LICENSE
pymoodleclient-0.2.0b1.dist-info/METADATA
pymoodleclient-0.2.0b1.dist-info/WHEEL
pymoodleclient-0.2.0b1.dist-info/RECORD
